[
  {
    "name": "지구당",
    "lat": 37.4782322,
    "lon": 126.9505673
  },
  {
    "name": "두만강 샤브샤브",
    "lat": 37.4787647,
    "lon": 126.9401629
  },
  {
    "name": "로향 양꼬치",
    "lat": 37.4799339,
    "lon": 126.95248
  },
  {
    "name": "성민 양꼬치",
    "lat": 37.479673,
    "lon": 126.9525063
  },
  {
    "name": "라멘남",
    "lat": 37.4778714,
    "lon": 126.940433
  },
  {
    "name": "아모카",
    "lat": 37.568257,
    "lon": 126.9736423
  },
  {
    "name": "만선 쭈꾸미",
    "lat": 37.57649,
    "lon": 126.9537481
  },
  {
    "name": "미진",
    "lat": 37.5705607,
    "lon": 126.9778025
  },
  {
    "name": "우래옥",
    "lat": 37.5681638,
    "lon": 126.9965592
  },
  {
    "name": "훌리오",
    "lat": 37.5488026,
    "lon": 126.9037305
  },
  {
    "name": "대명곱창",
    "lat": 37.556282,
    "lon": 127.079278
  },
  {
    "name": "달볶이",
    "lat": 37.5451483,
    "lon": 126.9634215
  },
  {
    "name": "명동 돈까스",
    "lat": 37.5639929,
    "lon": 126.9813796
  },
  {
    "name": "딘타이펑",
    "lat": 37.5643806,
    "lon": 126.980254
  },
  {
    "name": "타이오키드",
    "lat": 37.5346257,
    "lon": 126.9957557
  },
  {
    "name": "수지스",
    "lat": 37.5338827,
    "lon": 126.9867305
  },
  {
    "name": "투브로즈(TWO BROZ)",
    "lat": 37.53467,
    "lon": 126.9959123
  },
  {
    "name": "쟈니덤플링",
    "lat": 37.5338391,
    "lon": 126.9915218
  },
  {
    "name": "갓덴스시",
    "lat": 37.5338339,
    "lon": 126.9586911
  },
  {
    "name": "돈부리",
    "lat": 37.5519637,
    "lon": 126.9037619
  },
  {
    "name": "2046 팬스테이크",
    "lat": 37.5791432,
    "lon": 126.9840289
  },
  {
    "name": "마초쉐프",
    "lat": 37.5006981,
    "lon": 127.0104592
  },
  {
    "name": "구슬함박",
    "lat": 37.5482807,
    "lon": 126.9033182
  },
  {
    "name": "팔과이분의일",
    "lat": 37.5488026,
    "lon": 126.9037305
  },
  {
    "name": "빈103",
    "lat": 37.5021929,
    "lon": 127.0270986
  },
  {
    "name": "순희네빈대떡",
    "lat": 37.5705799,
    "lon": 126.9831984
  },
  {
    "name": "광장시장 마약김밥",
    "lat": 37.570038,
    "lon": 126.982094
  },
  {
    "name": "논현손칼국수",
    "lat": 37.5236685,
    "lon": 127.0215522
  },
  {
    "name": "스모키살룬",
    "lat": 37.5633408,
    "lon": 126.9806693
  },
  {
    "name": "곰스603",
    "lat": 37.5084734,
    "lon": 127.0154132
  },
  {
    "name": "십원집",
    "lat": 37.5634048,
    "lon": 126.973694
  },
  {
    "name": "백년옥",
    "lat": 37.481157,
    "lon": 127.0115575
  },
  {
    "name": "The뚝배기",
    "lat": 37.481157,
    "lon": 127.0115575
  },
  {
    "name": "히카리",
    "lat": 37.5448884,
    "lon": 126.9497817
  },
  {
    "name": "서울냉면",
    "lat": 37.5443524,
    "lon": 126.950201
  },
  {
    "name": "타궐안",
    "lat": 37.5586769,
    "lon": 126.920612
  },
  {
    "name": "완차이",
    "lat": 37.5586799,
    "lon": 126.9218524
  },
  {
    "name": "와플하우스",
    "lat": 37.5444217,
    "lon": 126.9510182
  },
  {
    "name": "신림 백순대",
    "lat": 37.4832501,
    "lon": 126.9112487
  }
]