{
"name": "삼성",
"children": [
	{"name": "건설 및 중공업",
	"children": [
		{"name": "삼성물산", "size":145500 },
		{"name": "삼성엔지니어링", "size":18300},
		{"name": "삼성중공업", "size":12850}
		]
	},
	{"name": "금융",
	"children": [
		{"name": "삼성벤처투자", "size":0},
		{"name": "삼성생명", "size":111500},
		{"name": "삼성자산운용", "size":0},
		{"name": "삼성증권", "size":45000},
		{"name": "삼성카드", "size":35100},
		{"name": "삼성화재", "size":320500}
		]
	},
	{"name": "서비스",
	"children": [
		{"name": "삼성경제연구소", "size":0},
		{"name": "삼성바이오에피스", "size":0},
		{"name": "삼성바이오로직스", "size":0},
		{"name": "삼성물산(건설 및 리조트)", "size":145500},
		{"name": "삼성물산(상사)", "size":145500},
		{"name": "삼성물산(패션)", "size":145500},
		{"name": "삼성웰스토리", "size":0},
		{"name": "삼성의료원", "size":0},
		{"name": "에스원", "size":92000},
		{"name": "제일기획", "size":19500},
		{"name": "호텔신라", "size":106500}
		]
	},
	{"name": "전자",
	"children": [
		{"name": "삼성SDI", "size":110000},
		{"name": "삼성SDS", "size":250000},
		{"name": "삼성디스플레이", "size":0},
		{"name": "삼성전기", "size":64000},
		{"name": "삼성코닝어드밴스드글라스", "size":0}
		]
	},
	{"name": "화학",
	"children": [
		{"name": "삼성BP화학", "size":0},
		{"name": "삼성정밀화학", "size":35850}
    	]
    }
	]
}